Workbook

Sheet Assumptions
A1: ⚡ EV Charging vs. Gas – Key Assumptions
A2: Parameter | B2: Value | C2: Notes / Source
A3: ── VEHICLE
A4: Tesla Model Y Year | B4: 2023 | C4: Both vehicles are 2023 MY
A5: White Tesla odometer (mi) | B5: 27000 | C5: As reported by Juan Perez
A6: Black Tesla odometer (mi) | B6: 21000 | C6: As reported by Juan Perez
A7: Combined monthly miles driven | B7: 1333 | C7: 48,000 mi ÷ 36 months (est. purchase Jan 2023)
A8: ── EV EFFICIENCY (miles / kWh)
A9: Summer efficiency (Aug–Sep) | B9: 4 | C9: Tesla Model Y 2023 EPA rating; warm temps
A10: Fall efficiency (Oct–Nov) | B10: 3.8 | C10: Cooler temps reduce range slightly
A11: Winter efficiency (Dec–Jan) | B11: 3.4 | C11: Cold weather significantly reduces battery range
A12: ── ELECTRICITY RATE
A13: Rate – Aug/Sep 2025 ($/kWh) | B13: 0.19 | C13: PSE&G standard supply ($0.18089) + delivery + taxes; Source: Arbor email Oct 3 2025
A14: Rate – Oct 2025 onward ($/kWh) | B14: 0.185 | C14: Arbor secured lower supply rate $0.17462 + delivery + taxes; Source: Arbor email Oct 3 2025
A15: ── GAS COMPARISON VEHICLE
A16: Comparison vehicle | B16: Toyota RAV4 AWD | C16: Closest gas SUV equivalent in class to Model Y
A17: Fuel economy (mpg combined) | B17: 30 | C17: 2023 Toyota RAV4 AWD EPA combined; Source: fueleconomy.gov
A18: ── NJ AVERAGE GAS PRICES (regular unleaded)
A19: August 2025 ($/gal) | B19: 3.1 | C19: NJ est. based on national avg $3.13; Source: BTS Motor Fuel Report Aug 2025
A20: September 2025 ($/gal) | B20: 3.15 | C20: NJ est. based on national avg $3.17; Source: BTS Motor Fuel Report Sep 2025
A21: October 2025 ($/gal) | B21: 3.02 | C21: NJ est. based on national avg $3.06; Source: BTS Motor Fuel Report Oct 2025
A22: November 2025 ($/gal) | B22: 2.99 | C22: NJ est. based on declining trend; Source: AAA / EIA historical data
A23: December 2025 ($/gal) | B23: 2.96 | C23: NJ est.; national avg $2.89, NJ slightly higher; Source: EIA
A24: January 2026 ($/gal) | B24: 2.93 | C24: NY–NJ metro BLS/FRED actual; Source: FRED APUS12A74714

Sheet Monthly Analysis
A1: Monthly EV Charging Cost vs. Gas Equivalent — Tesla Model Y (2023) | Maywood, NJ
B2: PSE&G Bill | C2: ⚡ EV Charging Details | H2: ⛽ Gas Equivalent | K2: 💰 Savings
A3: Month | B3: PSE&G Total Bill (Electric + Gas) | C3: EV Efficiency (mi / kWh) | D3: Monthly Miles (combined) | E3: kWh Used for EVs | F3: Electricity Rate ($/kWh) | G3: EV Charging Cost ($) | H3: NJ Gas Price ($/gal, regular) | I3: Gallons Equiv. (2× RAV4 @30mpg) | J3: Gas Equiv. Cost ($) | K3: Monthly Savings ($) | L3: Savings (%)
A4: August 2025 | B4: 492.76 | C4: =Assumptions!B9 -> 4 | D4: =Assumptions!B7 -> 1333 | E4: =D4/C4 -> 333.25 | F4: =Assumptions!B13 -> 0.19 | G4: =E4*F4 -> 63.3175 | H4: =Assumptions!B19 -> 3.1 | I4: =D4/Assumptions!B17 -> 44.433333 | J4: =I4*H4 -> 137.74333 | K4: =J4-G4 -> 74.425833 | L4: =IF(J4>0,K4/J4,0) -> 0.54032258
A5: September 2025 | B5: 253.53 | C5: =Assumptions!B9 -> 4 | D5: =Assumptions!B7 -> 1333 | E5: =D5/C5 -> 333.25 | F5: =Assumptions!B13 -> 0.19 | G5: =E5*F5 -> 63.3175 | H5: =Assumptions!B20 -> 3.15 | I5: =D5/Assumptions!B17 -> 44.433333 | J5: =I5*H5 -> 139.965 | K5: =J5-G5 -> 76.6475 | L5: =IF(J5>0,K5/J5,0) -> 0.54761905
A6: October 2025 | B6: 310.43 | C6: =Assumptions!B10 -> 3.8 | D6: =Assumptions!B7 -> 1333 | E6: =D6/C6 -> 350.78947 | F6: =Assumptions!B14 -> 0.185 | G6: =E6*F6 -> 64.896053 | H6: =Assumptions!B21 -> 3.02 | I6: =D6/Assumptions!B17 -> 44.433333 | J6: =I6*H6 -> 134.18867 | K6: =J6-G6 -> 69.292614 | L6: =IF(J6>0,K6/J6,0) -> 0.51638201
A7: November 2025 | B7: 496.4 | C7: =Assumptions!B10 -> 3.8 | D7: =Assumptions!B7 -> 1333 | E7: =D7/C7 -> 350.78947 | F7: =Assumptions!B14 -> 0.185 | G7: =E7*F7 -> 64.896053 | H7: =Assumptions!B22 -> 2.99 | I7: =D7/Assumptions!B17 -> 44.433333 | J7: =I7*H7 -> 132.85567 | K7: =J7-G7 -> 67.959614 | L7: =IF(J7>0,K7/J7,0) -> 0.51152966
A8: December 2025 | B8: 598.04 | C8: =Assumptions!B11 -> 3.4 | D8: =Assumptions!B7 -> 1333 | E8: =D8/C8 -> 392.05882 | F8: =Assumptions!B14 -> 0.185 | G8: =E8*F8 -> 72.530882 | H8: =Assumptions!B23 -> 2.96 | I8: =D8/Assumptions!B17 -> 44.433333 | J8: =I8*H8 -> 131.52267 | K8: =J8-G8 -> 58.991784 | L8: =IF(J8>0,K8/J8,0) -> 0.44852941
A9: January 2026 | B9: 714.72 | C9: =Assumptions!B11 -> 3.4 | D9: =Assumptions!B7 -> 1333 | E9: =D9/C9 -> 392.05882 | F9: =Assumptions!B14 -> 0.185 | G9: =E9*F9 -> 72.530882 | H9: =Assumptions!B24 -> 2.93 | I9: =D9/Assumptions!B17 -> 44.433333 | J9: =I9*H9 -> 130.18967 | K9: =J9-G9 -> 57.658784 | L9: =IF(J9>0,K9/J9,0) -> 0.44288296
A10: 6-MONTH TOTAL | B10: =SUM(B4:B9) -> 2865.88 | G10: =SUM(G4:G9) -> 401.48887 | J10: =SUM(J4:J9) -> 806.465 | K10: =SUM(K4:K9) -> 404.97613 | L10: =K10/J10 -> 0.50216207
A11: Monthly Average | B11: =AVERAGE(B4:B9) -> 477.64667 | G11: =AVERAGE(G4:G9) -> 66.914812 | J11: =AVERAGE(J4:J9) -> 134.41083 | K11: =AVERAGE(K4:K9) -> 67.496022 | L11: =AVERAGE(L4:L9) -> 0.50121095
A13: ℹ️ Notes: PSE&G Total Bill includes BOTH electricity and natural gas (heating). EV Charging Cost reflects only the electricity cost attributable to charging both Tesla Model Y's. Gas comparison uses Toyota RAV4 AWD (closest equivalent SUV). Efficiency adjusted for seasonal temperature effects on battery range.

Sheet Summary Dashboard
A1: ⚡ Tesla Model Y Charging vs. Gas — 6-Month Savings Dashboard
A2: Aug 2025 – Jan 2026 | Two 2023 Tesla Model Y's | Maywood, NJ | Compared to: Toyota RAV4 AWD (30 mpg)
B4: Total EV Charging Cost | D4: Total Gas Equiv. Cost | F4: Total Savings (6mo)
B5: ='Monthly Analysis'!G10 -> 401.48887 | D5: ='Monthly Analysis'!J10 -> 806.465 | F5: ='Monthly Analysis'!K10 -> 404.97613
B8: Avg Monthly EV Cost | D8: Avg Monthly Gas Cost | F8: Avg Monthly Savings
B9: ='Monthly Analysis'!G11 -> 66.914812 | D9: ='Monthly Analysis'!J11 -> 134.41083 | F9: ='Monthly Analysis'!K11 -> 67.496022
B12: 📅 Annualized Savings Projection
B13: Estimated Annual Savings | D13: ='Monthly Analysis'!K11*12 -> 809.95226 | F13: per year (estimated)
B14: Lifetime Savings (8yr ownership) | D14: ='Monthly Analysis'!K11*12*8 -> 6479.6181 | F14: over 8 years (vs. 2 gas SUVs)
B16: Sources: Gmail / PSE&G bill notifications | Arbor rate email (Oct 2025) | BTS Motor Fuel Price Reports | BLS/FRED NY-NJ Metro (APUS12A74714) | Tesla Model Y EPA efficiency | fueleconomy.gov
